LICENSE
MANIFEST.in
README.md
setup.py
mezzanine_portfolio.egg-info/PKG-INFO
mezzanine_portfolio.egg-info/SOURCES.txt
mezzanine_portfolio.egg-info/dependency_links.txt
mezzanine_portfolio.egg-info/top_level.txt
portfolio/__init__.py
portfolio/admin.py
portfolio/apps.py
portfolio/models.py
portfolio/translation.py
portfolio/urls.py
portfolio/views.py
portfolio/__pycache__/__init__.cpython-34.pyc
portfolio/__pycache__/admin.cpython-34.pyc
portfolio/__pycache__/models.cpython-34.pyc
portfolio/__pycache__/translation.cpython-34.pyc
portfolio/__pycache__/urls.cpython-34.pyc
portfolio/__pycache__/views.cpython-34.pyc
portfolio/migrations/0001_initial.py
portfolio/migrations/0002_portfolioimage.py
portfolio/migrations/__init__.py
portfolio/migrations/__pycache__/0001_initial.cpython-34.pyc
portfolio/migrations/__pycache__/0002_portfolioimage.cpython-34.pyc
portfolio/migrations/__pycache__/__init__.cpython-34.pyc
portfolio/templates/portfolio/portfolio_post_detail.html
portfolio/templates/portfolio/portfolio_post_list.html
portfolio/templatetags/__init__.py
portfolio/templatetags/portfolio_tags.py
portfolio/templatetags/__pycache__/__init__.cpython-34.pyc
portfolio/templatetags/__pycache__/portfolio_tags.cpython-34.pyc