Metadata-Version: 1.0
Name: mezzanine-portfolio
Version: 0.1
Summary: Django/Mezzanine portfolio application
Home-page: https://github.com/izhukov1992/mezzanine-portfolio
Author: Ilya Zhukov
Author-email: izhukov1992@gmail.com
License: BSD License
Platform: UNKNOWN
